ayame/__init__.py
ayame/__version__.py
ayame/app.py
ayame/basic.py
ayame/border.py
ayame/converter.py
ayame/core.py
ayame/exception.py
ayame/form.py
ayame/http.py
ayame/i18n.py
ayame/link.py
ayame/local.py
ayame/markup.py
ayame/model.py
ayame/page.py
ayame/panel.py
ayame/res.py
ayame/route.py
ayame/session.py
ayame/uri.py
ayame/util.py
ayame/validator.py
ayame/app/Ayame.properties
ayame/border/FeedbackFieldBorder.html
ayame/page/HTTPStatusPage.html
ayame/panel/FeedbackPanel.html
ayame-0.3.dist-info/LICENSE.txt
ayame-0.3.dist-info/METADATA
ayame-0.3.dist-info/WHEEL
ayame-0.3.dist-info/top_level.txt
ayame-0.3.dist-info/RECORD
