Metadata-Version: 2.1
Name: ayame
Version: 0.3
Summary: An Apache Wicket-like component based WSGI framework
Author-email: Akinori Hattori <hattya@gmail.com>
License: MIT
Project-URL: Homepage, https://github.com/hattya/ayame
Classifier: Development Status :: 3 - Alpha
Classifier: Environment :: Web Environment
Classifier: Intended Audience :: Developers
Classifier: License :: OSI Approved :: MIT License
Classifier: Operating System :: OS Independent
Classifier: Programming Language :: Python :: 3
Classifier: Programming Language :: Python :: 3.8
Classifier: Programming Language :: Python :: 3.9
Classifier: Programming Language :: Python :: 3.10
Classifier: Programming Language :: Python :: 3.11
Classifier: Programming Language :: Python :: 3.12
Classifier: Topic :: Internet :: WWW/HTTP :: Dynamic Content
Classifier: Topic :: Internet :: WWW/HTTP :: WSGI
Classifier: Topic :: Software Development :: Libraries :: Application Frameworks
Classifier: Topic :: Software Development :: Libraries :: Python Modules
Requires-Python: >=3.8
License-File: LICENSE.txt
Requires-Dist: Werkzeug
Requires-Dist: secure-cookie
